MANIFEST.in
README.md
setup.py
sentry_replay/__init__.py
sentry_replay/plugin.py
sentry_replay.egg-info/PKG-INFO
sentry_replay.egg-info/SOURCES.txt
sentry_replay.egg-info/dependency_links.txt
sentry_replay.egg-info/entry_points.txt
sentry_replay.egg-info/not-zip-safe
sentry_replay.egg-info/requires.txt
sentry_replay.egg-info/top_level.txt