Metadata-Version: 1.0
Name: sentry-replay
Version: 0.1.0
Summary: A Sentry extension which replay events to other Sentry
Home-page: http://code.gisce.net/sentry-replay
Author: Eduard Carreras
Author-email: ecarreras@gisce.net
License: BSD
Platform: UNKNOWN
Classifier: Framework :: Django
Classifier: Intended Audience :: Developers
Classifier: Intended Audience :: System Administrators
Classifier: Operating System :: OS Independent
Classifier: Topic :: Software Development
